[
    {
      "id": 1,
      "title": "Pan",
      "description": "Pan casero.",
      "price": 100,
      "thumbnail": "Sin imagen",
      "code": "code1",
      "stock": 50
    },
    {
      "id": 2,
      "title": "Queso",
      "description": "Queso cremoso.",
      "price": 200,
      "thumbnail": "Con imagen",
      "code": "code2",
      "stock": 100
    },
    {
      "id": 3,
      "title": "Jamón",
      "description": "Jamón cocido.",
      "price": 300,
      "thumbnail": "Sin imagen",
      "code": "code3",
      "stock": 150
    },
    {
      "id": 4,
      "title": "Leche",
      "description": "Leche de vaca.",
      "price": 400,
      "thumbnail": "Con imagen",
      "code": "code4",
      "stock": 200
    },
    {
      "id": 5,
      "title": "Carne",
      "description": "Carne picada.",
      "price": 500,
      "thumbnail": "Sin imagen",
      "code": "code5",
      "stock": 250
    },
    {
      "id": 6,
      "title": "Arroz",
      "description": "Arroz blanco.",
      "price": 600,
      "thumbnail": "Con imagen",
      "code": "code6",
      "stock": 300
    },
    {
      "id": 7,
      "title": "Tomate",
      "description": "Tomate fresco.",
      "price": 700,
      "thumbnail": "Sin imagen",
      "code": "code7",
      "stock": 350
    },
    {
      "id": 8,
      "title": "Lechuga",
      "description": "Lechuga fresca.",
      "price": 800,
      "thumbnail": "Con imagen",
      "code": "code8",
      "stock": 400
    },
    {
      "id": 9,
      "title": "Aceite",
      "description": "Aceite duradero.",
      "price": 900,
      "thumbnail": "Sin imagen",
      "code": "code9",
      "stock": 450
    },
    {
      "id": 10,
      "title": "Huevo",
      "description": "Huevo de calidad.",
      "price": 1000,
      "thumbnail": "Con imagen",
      "code": "code10",
      "stock": 500
    }
]